reloadwsgi.py
setup.cfg
setup.py
ReloadWSGI.egg-info/PKG-INFO
ReloadWSGI.egg-info/SOURCES.txt
ReloadWSGI.egg-info/dependency_links.txt
ReloadWSGI.egg-info/entry_points.txt
ReloadWSGI.egg-info/not-zip-safe
ReloadWSGI.egg-info/requires.txt
ReloadWSGI.egg-info/top_level.txt