Metadata-Version: 1.0
Name: ReloadWSGI
Version: 0.3
Summary: Robust WSGI auto-reloading for development.
Home-page: http://bitbucket.org/dholth/reloadwsgi/
Author: Daniel Holth
Author-email: dholth@fastmail.fm
License: MIT
Keywords: wsgi
Platform: UNKNOWN
Classifier: Intended Audience :: Developers
Classifier: Topic :: Internet :: WWW/HTTP :: WSGI
Classifier: Topic :: Internet :: WWW/HTTP :: WSGI :: Server
Classifier: Development Status :: 3 - Alpha
Classifier: License :: OSI Approved :: MIT License
